{
  "schemaVersion": 1,
  "id": "holdingskull",
  "version": "${version}",
  "name": "Skull that holds your items",
  "description": "Skull that holds your items on death",
  "authors": [
    "ThePotatoArchivist",
    "macuguita"
  ],
  "contact": {
    "homepage": "https://github.com/macuguita/SkullThatHoldsYourItems",
    "sources": "https://github.com/macuguita/SkullThatHoldsYourItems",
    "issues": "https://github.com/macuguita/SkullThatHoldsYourItems/issues"
  },
  "license": "CC0-1.0",
  "icon": "assets/holdingskull/icon.png",
  "environment": "*",
  "entrypoints": {
    "main": [
      "archives.tater.holdingskull.HoldingSkull"
    ],
    "client": [
      "archives.tater.holdingskull.client.HoldingSkullClient"
    ]
  },
  "mixins": [
    "holdingskull.mixins.json",
    {
      "config": "holdingskull.client.mixins.json",
      "environment": "client"
    }
  ],
  "accessWidener": "holdingskull.classtweaker",
  "depends": {
    "fabricloader": ">=0.18.0",
    "minecraft": "~26.1-",
    "java": ">=25",
    "fabric-api": "*"
  }
}